spanda_rag_toolkit/Spanda_Decompose.py
spanda_rag_toolkit/Spanda_Final_llm.py
spanda_rag_toolkit/Spanda_Reranker.py
spanda_rag_toolkit/Spanda_Summarizer.py
spanda_rag_toolkit/__init__.py
spanda_rag_toolkit-0.1.7.dist-info/METADATA
spanda_rag_toolkit-0.1.7.dist-info/WHEEL
spanda_rag_toolkit-0.1.7.dist-info/top_level.txt
spanda_rag_toolkit-0.1.7.dist-info/RECORD
